df_profiling/DF_Profiling.py
df_profiling/__init__.py
easy_df_profiling-0.1.2.dist-info/METADATA
easy_df_profiling-0.1.2.dist-info/WHEEL
easy_df_profiling-0.1.2.dist-info/top_level.txt
easy_df_profiling-0.1.2.dist-info/RECORD
