Metadata-Version: 2.1
Name: easy-df-profiling
Version: 0.1.2
Summary: A package that allows you to easily profile your dataframe, check for missing values, outliers, data types.
Home-page: UNKNOWN
Author: Sam Faraday
Author-email: <saurater@gmail.com>
License: MIT
Keywords: python,profiling,outliers,missing values
Platform: UNKNOWN
Classifier: Development Status :: 1 - Planning
Classifier: Intended Audience :: Developers
Classifier: Programming Language :: Python :: 3
Classifier: Operating System :: Unix
Classifier: Operating System :: MacOS :: MacOS X
Classifier: Operating System :: Microsoft :: Windows
Requires-Dist: pandas
